orappgen/__init__.py
orappgen/starter.py
orappgen-0.2.1.dist-info/LICENSE
orappgen-0.2.1.dist-info/METADATA
orappgen-0.2.1.dist-info/WHEEL
orappgen-0.2.1.dist-info/entry_points.txt
orappgen-0.2.1.dist-info/top_level.txt
orappgen-0.2.1.dist-info/RECORD
