Metadata-Version: 2.1
Name: orappgen
Version: 0.2.1
Summary: Générateur d'applications Django structurées (modèles, vues, urls...)
Home-page: UNKNOWN
Author: Benjamin
Author-email: benjamin@orjo.com
License: MIT
Platform: UNKNOWN
Classifier: Framework :: Django
Classifier: Programming Language :: Python :: 3
Classifier: License :: OSI Approved :: MIT License
Classifier: Operating System :: OS Independent
Requires-Python: >=3.7
License-File: LICENSE
Requires-Dist: Django>=3.2
